cv_net_library/__init__.py
cv_net_library/activation/ComplexActivation.py
cv_net_library/activation/__init__.py
cv_net_library/function/ComplexBatchNorm.py
cv_net_library/function/__init__.py
cv_net_library/layer/ComplexDropout.py
cv_net_library/layer/ComplexLayers.py
cv_net_library/layer/ComplexPooling.py
cv_net_library/layer/ComplexUpSampling.py
cv_net_library/layer/__init__.py
cv_net_library/loss/ComplexLoss.py
cv_net_library/loss/__init__.py
cv_net_library/model/__init__.py
cv_net_library/optimization/__init__.py
cv_net_library/solver/__init__.py
cv_net_library-0.0.3.dist-info/LICENSE.txt
cv_net_library-0.0.3.dist-info/METADATA
cv_net_library-0.0.3.dist-info/WHEEL
cv_net_library-0.0.3.dist-info/top_level.txt
cv_net_library-0.0.3.dist-info/RECORD
