Metadata-Version: 2.1
Name: cv_net_library
Version: 0.0.3
Summary: A library of complex-valued neural networks
Home-page: 
Author: XiaoDong Zhou
Author-email: zhou460749608@163.com
Classifier: Programming Language :: Python :: 3
Classifier: License :: OSI Approved :: MIT License
Classifier: Operating System :: OS Independent
Requires-Python: >=3.8
License-File: LICENSE.txt
